.coveragerc
.gitignore
.travis.yml
LICENSE
README.rst
setup.py
choke/__init__.py
choke/choke_base.py
choke/redis_choke.py
choke/simple_choke.py
choke.egg-info/PKG-INFO
choke.egg-info/SOURCES.txt
choke.egg-info/dependency_links.txt
choke.egg-info/requires.txt
choke.egg-info/top_level.txt
examples/basic_usage.py
tests/__init__.py
tests/test_redis_choke.py
tests/test_simple_choke.py