Metadata-Version: 1.0
Name: choke
Version: 0.1.2
Summary: choke: simple implementation of throttling mechanism.
Home-page: UNKNOWN
Author: Konrad Jałowiecki <dexter2206@gmail.com>
Author-email: dexter2206@gmail.com
License: MIT
Keywords: throttling redis limit
Platform: Linux
Platform: Unix
